AUTHORS
ChangeLog
LICENSE
README.rst
setup.cfg
setup.py
docs/images/animation.gif
horizon_monitoring/__init__.py
horizon_monitoring/dashboard.py
horizon_monitoring/models.py
horizon_monitoring/views.py
horizon_monitoring/aggregates/__init__.py
horizon_monitoring/aggregates/panel.py
horizon_monitoring/aggregates/tables.py
horizon_monitoring/aggregates/urls.py
horizon_monitoring/aggregates/views.py
horizon_monitoring/api/__init__.py
horizon_monitoring/api/base.py
horizon_monitoring/api/kedb.py
horizon_monitoring/api/sensu.py
horizon_monitoring/checks/__init__.py
horizon_monitoring/checks/forms.py
horizon_monitoring/checks/panel.py
horizon_monitoring/checks/tables.py
horizon_monitoring/checks/urls.py
horizon_monitoring/checks/views.py
horizon_monitoring/clients/__init__.py
horizon_monitoring/clients/panel.py
horizon_monitoring/clients/tables.py
horizon_monitoring/clients/urls.py
horizon_monitoring/clients/views.py
horizon_monitoring/errors/__init__.py
horizon_monitoring/errors/const.py
horizon_monitoring/errors/forms.py
horizon_monitoring/errors/panel.py
horizon_monitoring/errors/tables.py
horizon_monitoring/errors/urls.py
horizon_monitoring/errors/views.py
horizon_monitoring/events/__init__.py
horizon_monitoring/events/forms.py
horizon_monitoring/events/panel.py
horizon_monitoring/events/tables.py
horizon_monitoring/events/tabs.py
horizon_monitoring/events/urls.py
horizon_monitoring/events/views.py
horizon_monitoring/info/__init__.py
horizon_monitoring/info/panel.py
horizon_monitoring/info/tables.py
horizon_monitoring/info/urls.py
horizon_monitoring/info/views.py
horizon_monitoring/stashes/__init__.py
horizon_monitoring/stashes/panel.py
horizon_monitoring/stashes/tables.py
horizon_monitoring/stashes/urls.py
horizon_monitoring/stashes/views.py
horizon_monitoring/templates/base_fullscreen.html
horizon_monitoring/templates/horizon_monitoring/aggregates/index.html
horizon_monitoring/templates/horizon_monitoring/checks/_request.html
horizon_sensu_dashboard.egg-info/PKG-INFO
horizon_sensu_dashboard.egg-info/SOURCES.txt
horizon_sensu_dashboard.egg-info/dependency_links.txt
horizon_sensu_dashboard.egg-info/not-zip-safe
horizon_sensu_dashboard.egg-info/top_level.txt