Metadata-Version: 1.1
Name: horizon-sensu-dashboard
Version: 0.0.6
Summary: Horizon panels integrating Sensu monitoring and Known Error Database
Home-page: https://github.com/tcpcloud/horizon-sensu-panel
Author: Ales Komarek & Michael Kuty
Author-email: mail@majklk.cz
License: UNKNOWN
Platform: UNKNOWN
Classifier: Development Status :: 5 - Production/Stable
Classifier: Framework :: Django
Classifier: Environment :: OpenStack
Classifier: Intended Audience :: Developers
Classifier: License :: OSI Approved :: Apache Software License
Classifier: Operating System :: OS Independent
Classifier: Programming Language :: Python
Classifier: Programming Language :: Python :: 2.6
Classifier: Programming Language :: Python :: 2.7
Classifier: Programming Language :: Python :: 3
Classifier: Programming Language :: Python :: 3.3
Classifier: Programming Language :: Python :: 3.4
Classifier: Topic :: Software Development
Classifier: Topic :: Software Development :: Libraries :: Application Frameworks
